[
  {
    "inputs": [{ "internalType": "contract ILendingPool", "name": "_lendingPool", "type": "address" }],
    "stateMutability": "nonpayable",
    "type": "constructor"
  },
  {
    "inputs": [],
    "name": "BORROW_RATIO_DECIMALS",
    "outputs": [{ "internalType": "uint256", "name": "", "type": "uint256" }],
    "stateMutability": "view",
    "type": "function"
  },
  {
    "inputs": [{ "internalType": "address", "name": "asset", "type": "address" }],
    "name": "getConfiguration",
    "outputs": [
      {
        "components": [{ "internalType": "uint256", "name": "data", "type": "uint256" }],
        "internalType": "struct DataTypes.ReserveConfigurationMap",
        "name": "",
        "type": "tuple"
      }
    ],
    "stateMutability": "view",
    "type": "function"
  },
  {
    "inputs": [{ "internalType": "address", "name": "asset", "type": "address" }],
    "name": "getVDebtToken",
    "outputs": [{ "internalType": "address", "name": "", "type": "address" }],
    "stateMutability": "view",
    "type": "function"
  },
  {
    "inputs": [],
    "name": "lendingPool",
    "outputs": [{ "internalType": "contract ILendingPool", "name": "", "type": "address" }],
    "stateMutability": "view",
    "type": "function"
  },
  {
    "inputs": [
      { "internalType": "address", "name": "asset", "type": "address" },
      { "internalType": "address", "name": "shareAsset", "type": "address" },
      { "internalType": "address", "name": "lidoAddr", "type": "address" },
      { "internalType": "uint256", "name": "amount", "type": "uint256" },
      { "internalType": "uint256", "name": "interestRateMode", "type": "uint256" },
      { "internalType": "uint256", "name": "borrowRatio", "type": "uint256" },
      { "internalType": "uint256", "name": "loopCount", "type": "uint256" }
    ],
    "name": "lidoLoop",
    "outputs": [],
    "stateMutability": "nonpayable",
    "type": "function"
  },
  {
    "inputs": [{ "internalType": "address", "name": "asset", "type": "address" }],
    "name": "ltv",
    "outputs": [{ "internalType": "uint256", "name": "", "type": "uint256" }],
    "stateMutability": "view",
    "type": "function"
  },
  {
    "inputs": [
      { "internalType": "address", "name": "asset", "type": "address" },
      { "internalType": "uint256", "name": "amount", "type": "uint256" },
      { "internalType": "uint256", "name": "interestRateMode", "type": "uint256" },
      { "internalType": "uint256", "name": "borrowRatio", "type": "uint256" },
      { "internalType": "uint256", "name": "loopCount", "type": "uint256" }
    ],
    "name": "singleLoop",
    "outputs": [],
    "stateMutability": "nonpayable",
    "type": "function"
  },
  {
    "inputs": [
      { "internalType": "address", "name": "underlyingAsset", "type": "address" },
      { "internalType": "address", "name": "vaultAsset", "type": "address" },
      { "internalType": "uint256", "name": "amount", "type": "uint256" },
      { "internalType": "uint256", "name": "interestRateMode", "type": "uint256" },
      { "internalType": "uint256", "name": "borrowRatio", "type": "uint256" },
      { "internalType": "uint256", "name": "loopCount", "type": "uint256" }
    ],
    "name": "vaultLoop",
    "outputs": [],
    "stateMutability": "nonpayable",
    "type": "function"
  }
]
